RRAEs/__init__.py
RRAEs/config.py
RRAEs/AE_base/AE_base.py
RRAEs/AE_base/__init__.py
RRAEs/AE_classes/AE_classes.py
RRAEs/AE_classes/__init__.py
RRAEs/interpolation/__init__.py
RRAEs/interpolation/interpolation.py
RRAEs/tests/test_AE_classes_CNN.py
RRAEs/tests/test_AE_classes_MLP.py
RRAEs/tests/test_fitting_CNN.py
RRAEs/tests/test_fitting_MLP.py
RRAEs/tests/test_interpolators.py
RRAEs/tests/test_mains.py
RRAEs/tests/test_save.py
RRAEs/tests/test_stable_SVD.py
RRAEs/tests/test_wrappers.py
RRAEs/trackers/__init__.py
RRAEs/trackers/trackers.py
RRAEs/training_classes/__init__.py
RRAEs/training_classes/training_classes.py
RRAEs/utilities/__init__.py
RRAEs/utilities/utilities.py
RRAEs/wrappers/__init__.py
RRAEs/wrappers/wrappers.py
rraes-0.1.0.dist-info/METADATA
rraes-0.1.0.dist-info/WHEEL
rraes-0.1.0.dist-info/RECORD
