Metadata-Version: 2.4
Name: RRAEs
Version: 0.1.0
Summary:  A package that allows handling equinox models and training them easily. It also provides many pre-defined Autoencoders based on equinox.
Author-email: Jad Mounayer <jad.mounayer@outlook.com>
License: MIT
Requires-Python: >=3.10
Requires-Dist: dill
Requires-Dist: equinox
Requires-Dist: jax
Requires-Dist: jaxlib
Requires-Dist: jaxtyping
Requires-Dist: matplotlib
Requires-Dist: numpy
Requires-Dist: optax
Requires-Dist: pandas
Requires-Dist: prettytable
Requires-Dist: pytest
Requires-Dist: tqdm
